{
   "abstract" : "Blah blah blah",
   "author" : [
      "Scott Kiehn E<lt>sk.keenlinks@gmail.comE<gt>"
   ],
   "dynamic_config" : 0,
   "generated_by" : "App::ModuleBuildTiny version 0.013",
   "license" : [
      "perl_5"
   ],
   "meta-spec" : {
      "url" : "http://search.cpan.org/perldoc?CPAN::Meta::Spec",
      "version" : "2"
   },
   "name" : "Mojolicious-Plugin-TimeMoment",
   "prereqs" : {
      "configure" : {
         "requires" : {
            "Module::Build::Tiny" : "0.039"
         }
      },
      "develop" : {
         "requires" : {
            "App::ModuleBuildTiny" : "0.013"
         }
      },
      "runtime" : {
         "requires" : {
            "Mojolicious" : "6.20",
            "Time::Moment" : "0.38",
            "Time::y2038" : "20100403",
            "perl" : "5.008001"
         }
      },
      "test" : {
         "requires" : {
            "Test::More" : "0.98"
         }
      }
   },
   "provides" : {
      "Mojolicious::Plugin::TimeMoment" : {
         "file" : "lib/Mojolicious/Plugin/TimeMoment.pm",
         "version" : "0.05"
      }
   },
   "release_status" : "stable",
   "version" : "0.05",
   "x_serialization_backend" : "JSON::PP version 2.27300"
}
